taivutin/__init__.py
taivutin/arvain.py
taivutin/asteet.py
taivutin/muodot.py
taivutin/muotojen_lukeminen.py
taivutin/sanakirja.py
taivutin/taivutin.py
taivutin/trie.py
taivutin/utils.py
taivutin/vakiot.py
taivutin-0.1.3.dist-info/LICENSE
taivutin-0.1.3.dist-info/METADATA
taivutin-0.1.3.dist-info/WHEEL
taivutin-0.1.3.dist-info/entry_points.txt
taivutin-0.1.3.dist-info/top_level.txt
taivutin-0.1.3.dist-info/RECORD
