Metadata-Version: 2.1
Name: taivutin
Version: 0.1.3
Summary: Suomenkielinen sijataivutin - Case inflector for Finnish
Author-email: Théo Friberg <theo.friberg@helsinki.fi>
License: GNU LESSER GENERAL PUBLIC LICENSE
Project-URL: Homepage, https://version.helsinki.fi/thfr/taivutin
Keywords: inflector,taivutin,finnish,suomi,sijataivutus,case inflection,nominit,nominals,substantiivit,nouns
Classifier: License :: OSI Approved :: GNU Lesser General Public License v3 or later (LGPLv3+)
Classifier: Programming Language :: Python
Classifier: Programming Language :: Python :: 3
Requires-Python: >=3.9
License-File: LICENSE
